{
  "version": "5",
  "dialect": "mysql",
  "id": "0a642606-2bf6-4cb9-8bc6-fb99f692dab4",
  "prevId": "ebf93610-2438-4443-b7e5-676f00056b1b",
  "tables": {
    "laporan": {
      "name": "laporan",
      "columns": {
        "id": {
          "name": "id",
          "type": "varchar(36)",
          "primaryKey": false,
          "notNull": true,
          "autoincrement": false
        },
        "petugas_id": {
          "name": "petugas_id",
          "type": "varchar(36)",
          "primaryKey": false,
          "notNull": true,
          "autoincrement": false
        },
        "tanggal": {
          "name": "tanggal",
          "type": "date",
          "primaryKey": false,
          "notNull": true,
          "autoincrement": false
        },
        "lokasi": {
          "name": "lokasi",
          "type": "varchar(200)",
          "primaryKey": false,
          "notNull": true,
          "autoincrement": false
        },
        "jenis_kegiatan_id": {
          "name": "jenis_kegiatan_id",
          "type": "varchar(36)",
          "primaryKey": false,
          "notNull": true,
          "autoincrement": false
        },
        "jumlah_peserta": {
          "name": "jumlah_peserta",
          "type": "int",
          "primaryKey": false,
          "notNull": true,
          "autoincrement": false
        },
        "deskripsi": {
          "name": "deskripsi",
          "type": "text",
          "primaryKey": false,
          "notNull": false,
          "autoincrement": false
        },
        "dokumentasi_url": {
          "name": "dokumentasi_url",
          "type": "varchar(500)",
          "primaryKey": false,
          "notNull": false,
          "autoincrement": false
        },
        "status": {
          "name": "status",
          "type": "enum('menunggu','disetujui','ditolak','revisi')",
          "primaryKey": false,
          "notNull": true,
          "autoincrement": false,
          "default": "'menunggu'"
        },
        "catatan_verifikasi": {
          "name": "catatan_verifikasi",
          "type": "text",
          "primaryKey": false,
          "notNull": false,
          "autoincrement": false
        },
        "verifikator_id": {
          "name": "verifikator_id",
          "type": "varchar(36)",
          "primaryKey": false,
          "notNull": false,
          "autoincrement": false
        },
        "created_at": {
          "name": "created_at",
          "type": "timestamp",
          "primaryKey": false,
          "notNull": false,
          "autoincrement": false,
          "default": "(now())"
        },
        "updated_at": {
          "name": "updated_at",
          "type": "timestamp",
          "primaryKey": false,
          "notNull": false,
          "autoincrement": false,
          "onUpdate": true,
          "default": "(now())"
        }
      },
      "indexes": {
        "unik_laporan": {
          "name": "unik_laporan",
          "columns": [
            "petugas_id",
            "tanggal",
            "lokasi",
            "jenis_kegiatan_id"
          ],
          "isUnique": true
        },
        "idx_status": {
          "name": "idx_status",
          "columns": [
            "status"
          ],
          "isUnique": false
        },
        "idx_tanggal": {
          "name": "idx_tanggal",
          "columns": [
            "tanggal"
          ],
          "isUnique": false
        },
        "idx_petugas": {
          "name": "idx_petugas",
          "columns": [
            "petugas_id"
          ],
          "isUnique": false
        }
      },
      "foreignKeys": {
        "laporan_petugas_id_pengguna_id_fk": {
          "name": "laporan_petugas_id_pengguna_id_fk",
          "tableFrom": "laporan",
          "tableTo": "pengguna",
          "columnsFrom": [
            "petugas_id"
          ],
          "columnsTo": [
            "id"
          ],
          "onDelete": "restrict",
          "onUpdate": "no action"
        },
        "laporan_jenis_kegiatan_id_master_kegiatan_id_fk": {
          "name": "laporan_jenis_kegiatan_id_master_kegiatan_id_fk",
          "tableFrom": "laporan",
          "tableTo": "master_kegiatan",
          "columnsFrom": [
            "jenis_kegiatan_id"
          ],
          "columnsTo": [
            "id"
          ],
          "onDelete": "restrict",
          "onUpdate": "no action"
        },
        "laporan_verifikator_id_pengguna_id_fk": {
          "name": "laporan_verifikator_id_pengguna_id_fk",
          "tableFrom": "laporan",
          "tableTo": "pengguna",
          "columnsFrom": [
            "verifikator_id"
          ],
          "columnsTo": [
            "id"
          ],
          "onDelete": "set null",
          "onUpdate": "no action"
        }
      },
      "compositePrimaryKeys": {
        "laporan_id": {
          "name": "laporan_id",
          "columns": [
            "id"
          ]
        }
      },
      "uniqueConstraints": {},
      "checkConstraint": {}
    },
    "master_kegiatan": {
      "name": "master_kegiatan",
      "columns": {
        "id": {
          "name": "id",
          "type": "varchar(36)",
          "primaryKey": false,
          "notNull": true,
          "autoincrement": false
        },
        "nama": {
          "name": "nama",
          "type": "varchar(100)",
          "primaryKey": false,
          "notNull": true,
          "autoincrement": false
        },
        "kode": {
          "name": "kode",
          "type": "varchar(30)",
          "primaryKey": false,
          "notNull": true,
          "autoincrement": false
        },
        "deskripsi": {
          "name": "deskripsi",
          "type": "text",
          "primaryKey": false,
          "notNull": false,
          "autoincrement": false
        },
        "aktif": {
          "name": "aktif",
          "type": "enum('y','n')",
          "primaryKey": false,
          "notNull": true,
          "autoincrement": false,
          "default": "'y'"
        },
        "created_at": {
          "name": "created_at",
          "type": "timestamp",
          "primaryKey": false,
          "notNull": false,
          "autoincrement": false,
          "default": "(now())"
        },
        "updated_at": {
          "name": "updated_at",
          "type": "timestamp",
          "primaryKey": false,
          "notNull": false,
          "autoincrement": false,
          "onUpdate": true,
          "default": "(now())"
        }
      },
      "indexes": {},
      "foreignKeys": {},
      "compositePrimaryKeys": {
        "master_kegiatan_id": {
          "name": "master_kegiatan_id",
          "columns": [
            "id"
          ]
        }
      },
      "uniqueConstraints": {
        "master_kegiatan_kode_unique": {
          "name": "master_kegiatan_kode_unique",
          "columns": [
            "kode"
          ]
        }
      },
      "checkConstraint": {}
    },
    "pengguna": {
      "name": "pengguna",
      "columns": {
        "id": {
          "name": "id",
          "type": "varchar(36)",
          "primaryKey": false,
          "notNull": true,
          "autoincrement": false
        },
        "nama": {
          "name": "nama",
          "type": "varchar(100)",
          "primaryKey": false,
          "notNull": true,
          "autoincrement": false
        },
        "email": {
          "name": "email",
          "type": "varchar(150)",
          "primaryKey": false,
          "notNull": true,
          "autoincrement": false
        },
        "password_hash": {
          "name": "password_hash",
          "type": "text",
          "primaryKey": false,
          "notNull": true,
          "autoincrement": false
        },
        "role": {
          "name": "role",
          "type": "enum('petugas','kepala_bidang','admin','pimpinan')",
          "primaryKey": false,
          "notNull": true,
          "autoincrement": false
        },
        "unit_kerja_id": {
          "name": "unit_kerja_id",
          "type": "varchar(36)",
          "primaryKey": false,
          "notNull": false,
          "autoincrement": false
        },
        "aktif": {
          "name": "aktif",
          "type": "enum('y','n')",
          "primaryKey": false,
          "notNull": true,
          "autoincrement": false,
          "default": "'y'"
        },
        "created_at": {
          "name": "created_at",
          "type": "timestamp",
          "primaryKey": false,
          "notNull": false,
          "autoincrement": false,
          "default": "(now())"
        },
        "updated_at": {
          "name": "updated_at",
          "type": "timestamp",
          "primaryKey": false,
          "notNull": false,
          "autoincrement": false,
          "onUpdate": true,
          "default": "(now())"
        }
      },
      "indexes": {},
      "foreignKeys": {
        "pengguna_unit_kerja_id_unit_kerja_id_fk": {
          "name": "pengguna_unit_kerja_id_unit_kerja_id_fk",
          "tableFrom": "pengguna",
          "tableTo": "unit_kerja",
          "columnsFrom": [
            "unit_kerja_id"
          ],
          "columnsTo": [
            "id"
          ],
          "onDelete": "set null",
          "onUpdate": "no action"
        }
      },
      "compositePrimaryKeys": {
        "pengguna_id": {
          "name": "pengguna_id",
          "columns": [
            "id"
          ]
        }
      },
      "uniqueConstraints": {
        "pengguna_email_unique": {
          "name": "pengguna_email_unique",
          "columns": [
            "email"
          ]
        }
      },
      "checkConstraint": {}
    },
    "unit_kerja": {
      "name": "unit_kerja",
      "columns": {
        "id": {
          "name": "id",
          "type": "varchar(36)",
          "primaryKey": false,
          "notNull": true,
          "autoincrement": false
        },
        "nama": {
          "name": "nama",
          "type": "varchar(100)",
          "primaryKey": false,
          "notNull": true,
          "autoincrement": false
        },
        "kode": {
          "name": "kode",
          "type": "varchar(20)",
          "primaryKey": false,
          "notNull": true,
          "autoincrement": false
        },
        "created_at": {
          "name": "created_at",
          "type": "timestamp",
          "primaryKey": false,
          "notNull": false,
          "autoincrement": false,
          "default": "(now())"
        },
        "updated_at": {
          "name": "updated_at",
          "type": "timestamp",
          "primaryKey": false,
          "notNull": false,
          "autoincrement": false,
          "onUpdate": true,
          "default": "(now())"
        }
      },
      "indexes": {},
      "foreignKeys": {},
      "compositePrimaryKeys": {
        "unit_kerja_id": {
          "name": "unit_kerja_id",
          "columns": [
            "id"
          ]
        }
      },
      "uniqueConstraints": {
        "unit_kerja_kode_unique": {
          "name": "unit_kerja_kode_unique",
          "columns": [
            "kode"
          ]
        }
      },
      "checkConstraint": {}
    }
  },
  "views": {},
  "_meta": {
    "schemas": {},
    "tables": {},
    "columns": {}
  },
  "internal": {
    "tables": {},
    "indexes": {}
  }
}